{
  "$schema": "https://schema.management.azure.com/schemas/2019-04-01/deploymentTemplate.json#",
  "contentVersion": "1.0.0.0",
  "resources": [
    {
      "type": "Microsoft.DocumentDB/databaseAccounts",
      "apiVersion": "2021-05-15",
      "name": "[concat('csmsarm', uniqueString(resourceGroup().id))]",
      "location": "[resourceGroup().location]",
      "properties": {
        "databaseAccountOfferType": "Standard",
        "locations": [
          {
            "locationName": "westus"
          }
        ]
      }
    }
    ,
    {
      "type": "Microsoft.DocumentDB/databaseAccounts/sqlDatabases",
      "apiVersion": "2021-05-15",
      "name": "[concat('csmsarm', uniqueString(resourceGroup().id), '/cosmicworks')]",
      "dependsOn": [
        "[resourceId('Microsoft.DocumentDB/databaseAccounts', concat('csmsarm', uniqueString(resourceGroup().id)))]"
      ],
      "properties": {
        "resource": {
          "id": "cosmicworks"
        }
      }
    }
    ,
    {
      "type": "Microsoft.DocumentDB/databaseAccounts/sqlDatabases/containers",
      "apiVersion": "2021-05-15",
      "name": "[concat('csmsarm', uniqueString(resourceGroup().id), '/cosmicworks/products')]",
      "dependsOn": [
        "[resourceId('Microsoft.DocumentDB/databaseAccounts', concat('csmsarm', uniqueString(resourceGroup().id)))]",
        "[resourceId('Microsoft.DocumentDB/databaseAccounts/sqlDatabases', concat('csmsarm', uniqueString(resourceGroup().id)), 'cosmicworks')]"
      ],
      "properties": {
        "options": {
          "throughput": 400
        },
        "resource": {
          "id": "products",
          "partitionKey": {
            "paths": [
              "/categoryId"
            ]
          }
          ,
          "indexingPolicy": {
            "indexingMode": "consistent",
            "automatic": true,
            "includedPaths": [
              {
                "path": "/price/*"
              }
            ],
            "excludedPaths": [
              {
                "path": "/*"
              }
            ]
          }
        }
      }
    }
  ]
}